{
	"folders": {},
	"connections": {
		"sqlite_jdbc-17b1234450d-61470e77a4094c65": {
			"provider": "generic",
			"driver": "sqlite_jdbc",
			"name": "db-sqlite3",
			"save-password": true,
			"navigator-show-only-entities": true,
			"navigator-hide-folders": true,
			"navigator-hide-virtual": true,
			"read-only": false,
			"configuration": {
				"database": "/home/daniel/Public/chercheurdart_2/source/ware/db/db-sqlite3",
				"url": "jdbc:sqlite:/home/daniel/Public/chercheurdart_2/source/ware/db/db-sqlite3",
				"type": "dev",
				"auth-model": "native"
			}
		}
	},
	"connection-types": {
		"dev": {
			"name": "Development",
			"color": "255,255,255",
			"description": "Regular development database",
			"auto-commit": true,
			"confirm-execute": false,
			"confirm-data-change": false,
			"auto-close-transactions": false
		}
	}
}